setup.py
av_agent_utils/__init__.py
av_agent_utils/kinesis.py
av_agent_utils/sts.py
av_agent_utils.egg-info/PKG-INFO
av_agent_utils.egg-info/SOURCES.txt
av_agent_utils.egg-info/dependency_links.txt
av_agent_utils.egg-info/namespace_packages.txt
av_agent_utils.egg-info/requires.txt
av_agent_utils.egg-info/top_level.txt
av_agent_utils.egg-info/zip-safe
scripts/agent-lookup-streams
scripts/agent-validate-sts-tokens
scripts/foo.config